LICENSE
README.md
setup.py
gh2db/__init__.py
gh2db/__main__.py
gh2db/dbbase.py
gh2db/logger.py
gh2db/migration.py
gh2db/model.py
gh2db.egg-info/PKG-INFO
gh2db.egg-info/SOURCES.txt
gh2db.egg-info/dependency_links.txt
gh2db.egg-info/entry_points.txt
gh2db.egg-info/top_level.txt